chat_export/__init__.py
chat_export/chat_export.py
chat_export-1.0.5.dist-info/licenses/LICENSE
chat_export-1.0.5.dist-info/METADATA
chat_export-1.0.5.dist-info/WHEEL
chat_export-1.0.5.dist-info/entry_points.txt
chat_export-1.0.5.dist-info/top_level.txt
chat_export-1.0.5.dist-info/RECORD
