Metadata-Version: 2.4
Name: chat-export
Version: 1.0.5
Summary: Convert WhatsApp chat exports to HTML format
Author-email: matlon GmbH <software@matlon.ch>
License: MIT License
Project-URL: Homepage, https://chat-export.click
Project-URL: Repository, https://github.com/mtln/chat-export
Project-URL: Issues, https://github.com/mtln/chat-export/issues
Project-URL: Donate, https://donate.stripe.com/3cI8wO0yD8Wt0ItbV06J204
Keywords: whatsapp,chat,export,html,conversion,archive
Classifier: Development Status :: 5 - Production/Stable
Classifier: Intended Audience :: End Users/Desktop
Classifier: License :: OSI Approved :: MIT License
Classifier: Operating System :: OS Independent
Classifier: Programming Language :: Python :: 3
Classifier: Programming Language :: Python :: 3.7
Classifier: Programming Language :: Python :: 3.8
Classifier: Programming Language :: Python :: 3.9
Classifier: Programming Language :: Python :: 3.10
Classifier: Programming Language :: Python :: 3.11
Classifier: Programming Language :: Python :: 3.12
Classifier: Programming Language :: Python :: 3.13
Classifier: Topic :: Communications :: Chat
Classifier: Topic :: Text Processing :: Markup :: HTML
Classifier: Topic :: Utilities
Classifier: Topic :: System :: Archiving
Requires-Python: >=3.7
License-File: LICENSE
Provides-Extra: macos
Requires-Dist: pyobjc-framework-Cocoa>=9.0; extra == "macos"
Provides-Extra: windows
Requires-Dist: pywin32>=306; extra == "windows"
Dynamic: license-file
